robot_soccer_python/__init__.py
robot_soccer_python/agents.py
robot_soccer_python/constants.py
robot_soccer_python/simulation.py
robot_soccer_python/simulation2D.py
robot_soccer_python/state_machine_ball.py
robot_soccer_python/test.py
robot_soccer_python/utils.py
robot_soccer_python-1.0.7.dist-info/LICENSE.txt
robot_soccer_python-1.0.7.dist-info/METADATA
robot_soccer_python-1.0.7.dist-info/WHEEL
robot_soccer_python-1.0.7.dist-info/top_level.txt
robot_soccer_python-1.0.7.dist-info/RECORD
